turbodash/__init__.py
turbodash/app.py
turbodash/app_lite.py
turbodash/core.py
turbodash/geom_blade.py
turbodash/graphics.py
turbodash/plotting_mpl.py
turbodash/plotting_plotly.py
turbodash_core-0.3.3.dist-info/LICENSE.md
turbodash_core-0.3.3.dist-info/METADATA
turbodash_core-0.3.3.dist-info/WHEEL
turbodash_core-0.3.3.dist-info/entry_points.txt
turbodash_core-0.3.3.dist-info/RECORD
