Metadata-Version: 2.1
Name: turbodash-core
Version: 0.3.3
Summary: Interactive Dash app for turbomachinery stage preliminary design
Home-page: https://github.com/turbo-sim/turbodash
License: MIT
Author: Roberto Agromayor
Requires-Python: >=3.11,<3.14
Classifier: License :: OSI Approved :: MIT License
Classifier: Programming Language :: Python :: 3
Classifier: Programming Language :: Python :: 3.11
Classifier: Programming Language :: Python :: 3.12
Requires-Dist: dash (>=3.2.0,<4.0.0)
Requires-Dist: gunicorn (>=22.0.0,<23.0.0)
Requires-Dist: jaxprop (>=0.5.2,<0.6.0)
Requires-Dist: matplotlib (>=3.10.6,<4.0.0)
Requires-Dist: numpy (>=2.3.0,<3.0.0)
Requires-Dist: plotly (>=5.23.0,<6.0.0)
Requires-Dist: python-docx (>=1.2.0,<2.0.0)
Requires-Dist: scipy (>=1.16.1,<2.0.0)
Project-URL: Documentation, https://github.com/turbo-sim/turbodash
Project-URL: Repository, https://github.com/turbo-sim/turbodash
